tsp/__init__.py
tsp/__meta__.py
tsp/concatenation.py
tsp/core.py
tsp/gtnp.py
tsp/labels.py
tsp/misc.py
tsp/physics.py
tsp/time.py
tsp/tspwarnings.py
tsp/utils.py
tsp/version.py
tsp/writers.py
tsp/data/2023-01-06_755-test-Dataset_2031-Constant_Over_Interval-Hourly-Ground_Temperature-Thermistor_Automated.timeserie.csv
tsp/data/2023-01-06_755-test.metadata.txt
tsp/data/NTGS_example_csv.csv
tsp/data/NTGS_example_slash_dates.csv
tsp/data/NTGS_gtr_example_excel.xlsx
tsp/data/example_geotop.csv
tsp/data/example_gtnp.csv
tsp/data/example_permos.csv
tsp/data/gtnp2026-multi.csv
tsp/data/gtnp2026-multi_metadata.json
tsp/data/gtnp2026.csv
tsp/data/gtnp2026_metadata.json
tsp/data/ntgs-db-multi.txt
tsp/data/ntgs-db-single.txt
tsp/data/test_geotop_has_space.txt
tsp/data/tsp_format_long.csv
tsp/data/tsp_format_wide_1.csv
tsp/data/tsp_format_wide_2.csv
tsp/dataloggers/AbstractReader.py
tsp/dataloggers/FG2.py
tsp/dataloggers/GP5W.py
tsp/dataloggers/Geoprecision.py
tsp/dataloggers/HOBO.py
tsp/dataloggers/RBRXL800.py
tsp/dataloggers/RBRXR420.py
tsp/dataloggers/Vemco.py
tsp/dataloggers/__init__.py
tsp/dataloggers/logr.py
tsp/dataloggers/test_files/004448.DAT
tsp/dataloggers/test_files/004531.DAT
tsp/dataloggers/test_files/004531.HEX
tsp/dataloggers/test_files/004534.HEX
tsp/dataloggers/test_files/010252.dat
tsp/dataloggers/test_files/010252.hex
tsp/dataloggers/test_files/010274.hex
tsp/dataloggers/test_files/010278.hex
tsp/dataloggers/test_files/012064.dat
tsp/dataloggers/test_files/012064.hex
tsp/dataloggers/test_files/012064_modified_start.hex
tsp/dataloggers/test_files/012081.hex
tsp/dataloggers/test_files/013138_recovery_stamp.hex
tsp/dataloggers/test_files/014037-2007.hex
tsp/dataloggers/test_files/019360_20160918_1146_SlumpIslandTopofHill.hex
tsp/dataloggers/test_files/019360_20160918_1146_SlumpIslandTopofHill.xls
tsp/dataloggers/test_files/062834_20220904_2351.rsk
tsp/dataloggers/test_files/062834_20220904_2351.xlsx
tsp/dataloggers/test_files/07B1592.DAT
tsp-1.10.4.dist-info/licenses/LICENSE
tsp-1.10.4.dist-info/METADATA
tsp-1.10.4.dist-info/WHEEL
tsp-1.10.4.dist-info/top_level.txt
tsp-1.10.4.dist-info/RECORD
