Metadata-Version: 2.4
Name: tsp
Version: 1.10.4
Summary: Making permafrost data effortless
Home-page: https://gitlab.com/permafrostnet/teaspoon
Author: Nick Brown
Author-email: nick.brown@carleton.ca
Classifier: Development Status :: 4 - Beta
Classifier: Intended Audience :: Developers
Classifier: License :: OSI Approved :: GNU General Public License (GPL)
Classifier: Operating System :: POSIX
Classifier: Programming Language :: Python
Classifier: Topic :: Software Development :: Libraries
License-File: LICENSE
Requires-Dist: pandas
Requires-Dist: numpy
Requires-Dist: regex
Requires-Dist: matplotlib
Requires-Dist: setuptools
Requires-Dist: netCDF4
Requires-Dist: pfit>=0.3.0
Requires-Dist: scipy
Requires-Dist: pyrsktools
Requires-Dist: openpyxl
Provides-Extra: nc
Requires-Dist: netCDF4; extra == "nc"
Requires-Dist: pfit>=0.3.0; extra == "nc"
Provides-Extra: plotting
Requires-Dist: scipy; extra == "plotting"
Provides-Extra: rbr
Requires-Dist: pyrsktools; extra == "rbr"
Requires-Dist: openpyxl; extra == "rbr"
Provides-Extra: full
Requires-Dist: pyrsktools; extra == "full"
Requires-Dist: openpyxl; extra == "full"
Requires-Dist: pfit>=0.3.0; extra == "full"
Requires-Dist: scipy; extra == "full"
Requires-Dist: netCDF4; extra == "full"
Provides-Extra: dev
Requires-Dist: manuel; extra == "dev"
Requires-Dist: pytest; extra == "dev"
Requires-Dist: pytest-cov; extra == "dev"
Requires-Dist: coverage; extra == "dev"
Requires-Dist: mock; extra == "dev"
Dynamic: author
Dynamic: author-email
Dynamic: classifier
Dynamic: description
Dynamic: description-content-type
Dynamic: home-page
Dynamic: license-file
Dynamic: provides-extra
Dynamic: requires-dist
Dynamic: summary
